typerighter/__init__.py
typerighter/cache.py
typerighter/exceptions.py
typerighter/schematics.py
typerighter/views.py
typerighter/types/__init__.py
typerighter/types/base.py
typerighter/types/composites.py
typerighter/types/cryptography.py
typerighter/types/domains.py
typerighter/types/ids.py
typerighter/types/net.py
typerighter/types/paths.py
typerighter/types/primitives.py
typerighter/types/records.py
typerighter/types/spatial.py
typerighter/types/timekeeping.py
typerighter-0.1.4.dist-info/METADATA
typerighter-0.1.4.dist-info/WHEEL
typerighter-0.1.4.dist-info/top_level.txt
typerighter-0.1.4.dist-info/RECORD
